openvpn_ipdb/__init__.py
openvpn_ipdb/client_connect.py
openvpn_ipdb/client_disconnect.py
openvpn_ipdb/lease_controller.py
openvpn_ipdb/lease_manager.py
openvpn_ipdb/sql/leases_v4.sql
openvpn_ipdb/sql/leases_v6.sql
openvpn_ipdb-1.0.0.dist-info/LICENSE.md
openvpn_ipdb-1.0.0.dist-info/METADATA
openvpn_ipdb-1.0.0.dist-info/WHEEL
openvpn_ipdb-1.0.0.dist-info/entry_points.txt
openvpn_ipdb-1.0.0.dist-info/top_level.txt
openvpn_ipdb-1.0.0.dist-info/RECORD
