Metadata-Version: 2.1
Name: openvpn-ipdb
Version: 1.0.0
Summary: Utility for managing OpenVPN IP address assignments
Home-page: https://gitlab.com/MatthiasLohr/openvpn-ipdb
Author: Matthias Lohr
Author-email: mail@mlohr.com
License: GPLv3
Project-URL: Bug Tracker, https://gitlab.com/MatthiasLohr/openvpn-ipdb/issues
Project-URL: Source Code, https://gitlab.com/MatthiasLohr/openvpn-ipdb/tree/master
Platform: UNKNOWN
Classifier: Development Status :: 5 - Production/Stable
Classifier: Environment :: Console
Classifier: Intended Audience :: System Administrators
Classifier: License :: OSI Approved :: GNU General Public License v3 (GPLv3)
Classifier: Programming Language :: Python :: 2
Classifier: Programming Language :: Python :: 2.7
Classifier: Topic :: System :: Networking
Requires-Python: ==2.7.*
Requires-Dist: netaddr (>=0.7.19)
